deepmodels/__init__.py
deepmodels/meta_tester.py
deepmodels/core/__init__.py
deepmodels/core/commons.py
deepmodels/core/tools.py
deepmodels/core/applications/__init__.py
deepmodels/core/data/__init__.py
deepmodels/core/data/commons.py
deepmodels/core/data/vision/__init__.py
deepmodels/core/data/vision/img_clf_data.py
deepmodels/core/data/vision/img_det_data.py
deepmodels/core/data/vision/img_gen_data.py
deepmodels/core/data/vision/match_data.py
deepmodels/core/data/vision/test_dataset.py
deepmodels/core/learners/__init__.py
deepmodels/core/learners/commons.py
deepmodels/core/learners/img_classifier.py
deepmodels/core/learners/img_gan.py
deepmodels/core/learners/img_matcher.py
deepmodels/core/models/__init__.py
deepmodels/core/models/commons.py
deepmodels/core/models/vision/__init__.py
deepmodels/core/models/vision/alexnet.py
deepmodels/core/models/vision/commons.py
deepmodels/core/models/vision/inception.py
deepmodels/core/models/vision/inception_resnet.py
deepmodels/core/models/vision/mobilenet.py
deepmodels/core/models/vision/resnet.py
deepmodels/core/models/vision/vgg.py
deepmodels/core/tests/__init__.py
deepmodels/core/tests/test_data.py
deepmodels/core/tests/test_dm_model.py
deepmodels/core/tests/test_learners.py
deepmodels/core/tests/test_model.py
deepmodels/data/__init__.py
deepmodels/data/cifar_data.py
deepmodels/data/data_test.py
deepmodels/data/mnist_data.py
deepmodels/engine/__init__.py
deepmodels/engine/keras/__init__.py
deepmodels/engine/keras/common.py
deepmodels/engine/keras/data/__init__.py
deepmodels/engine/keras/data/vision/__init__.py
deepmodels/engine/keras/data/vision/img_clf_data.py
deepmodels/engine/keras/data/vision/img_det_data.py
deepmodels/engine/keras/data/vision/img_gen_data.py
deepmodels/engine/keras/learners/__init__.py
deepmodels/engine/keras/learners/img_classifier.py
deepmodels/engine/keras/learners/img_gan.py
deepmodels/engine/keras/models/__init__.py
deepmodels-0.3.2.dist-info/DESCRIPTION.rst
deepmodels-0.3.2.dist-info/METADATA
deepmodels-0.3.2.dist-info/RECORD
deepmodels-0.3.2.dist-info/WHEEL
deepmodels-0.3.2.dist-info/metadata.json
deepmodels-0.3.2.dist-info/top_level.txt
