Metadata-Version: 2.0
Name: deepmodels
Version: 0.3.2
Summary: framework for build, train and test deep learning models
Home-page: https://flyfj@bitbucket.org/teamperceptance/deepmodels.git
Author: Jie Feng
Author-email: jiefengdev@gmail.com
License: MIT
Platform: UNKNOWN
Requires-Dist: backports.weakref (==1.0.post1)
Requires-Dist: bleach (==1.5.0)
Requires-Dist: botocore (==1.5.33)
Requires-Dist: colorama (==0.3.7)
Requires-Dist: cycler (==0.10.0)
Requires-Dist: decorator (==4.0.11)
Requires-Dist: docutils (==0.14)
Requires-Dist: enum34 (==1.1.6)
Requires-Dist: funcsigs (==1.0.2)
Requires-Dist: functools32 (==3.2.3.post2)
Requires-Dist: futures (==3.2.0)
Requires-Dist: GPUtil (==1.2.3)
Requires-Dist: h5py (==2.7.1)
Requires-Dist: html5lib (==0.9999999)
Requires-Dist: jmespath (==0.9.3)
Requires-Dist: Keras (==2.1.2)
Requires-Dist: keras-resnet (==0.0.8)
Requires-Dist: Markdown (==2.6.9)
Requires-Dist: matplotlib (==2.0.2)
Requires-Dist: mock (==2.0.0)
Requires-Dist: networkx (==1.11)
Requires-Dist: numpy (==1.13.3)
Requires-Dist: olefile (==0.44)
Requires-Dist: opencv-python (==3.3.0.10)
Requires-Dist: pbr (==3.1.1)
Requires-Dist: Pillow (==4.1.1)
Requires-Dist: protobuf (==3.5.0.post1)
Requires-Dist: py (==1.4.34)
Requires-Dist: pyasn1 (==0.3.4)
Requires-Dist: pyparsing (==2.2.0)
Requires-Dist: pytest (==3.2.2)
Requires-Dist: python-dateutil (==2.6.0)
Requires-Dist: pytz (==2017.2)
Requires-Dist: PyWavelets (==0.5.2)
Requires-Dist: PyYAML (==3.12)
Requires-Dist: rsa (==3.4.2)
Requires-Dist: scikit-image (==0.13.0)
Requires-Dist: scikit-learn (==0.18.1)
Requires-Dist: scipy (==1.0.0)
Requires-Dist: six (==1.11.0)
Requires-Dist: subprocess32 (==3.2.7)
Requires-Dist: tensorflow-gpu (==1.4.0)
Requires-Dist: tensorflow-tensorboard (==0.4.0rc3)
Requires-Dist: Theano (==0.9.0)
Requires-Dist: tqdm (==4.14.0)
Requires-Dist: Werkzeug (==0.12.2)
